autosink_data_preparation/__init__.py
autosink_data_preparation/path/autosink.py
autosink_data_preparation/path/backends.py
autosink_data_preparation/path/base.py
autosink_data_preparation/subpackage/__init__.py
autosink_data_preparation/subpackage/hello.py
autosink_data_preparation/subpackage/test_hello.py
autosink_data_preparation-0.3.1.dist-info/WHEEL
autosink_data_preparation-0.3.1.dist-info/METADATA
autosink_data_preparation-0.3.1.dist-info/RECORD
