Metadata-Version: 2.1
Name: autosink-data-preparation
Version: 0.3.1
Summary: 
Author-email: Janghoo Lee <dlwkdgn1@naver.com>
Requires-Python: >=3.8
Classifier: License :: OSI Approved :: MIT License
Requires-Dist: PyYAML
Requires-Dist: flit ; extra == "dev"
Requires-Dist: pylint ; extra == "dev"
Requires-Dist: yapf ; extra == "dev"
Provides-Extra: dev
